swga/__init__.py
swga/database.py
swga/export.py
swga/graph.py
swga/kmers.py
swga/locate.py
swga/primers.py
swga/score.py
swga/stats.py
swga/utils.py
swga/bin/dsk
swga/bin/set_finder
swga/commands/__init__.py
swga/commands/_command.py
swga/commands/activate.py
swga/commands/count.py
swga/commands/export.py
swga/commands/filter.py
swga/commands/find_sets.py
swga/commands/init.py
swga/commands/score.py
swga/commands/summary.py
swga/commands/swga_entry.py
swga/commands/specfiles/activate.yaml
swga/commands/specfiles/count.yaml
swga/commands/specfiles/export.yaml
swga/commands/specfiles/filter.yaml
swga/commands/specfiles/find_sets.yaml
swga/commands/specfiles/score.yaml
swga/commands/specfiles/summary.yaml
swga-0.4.0.data/data/bin/dsk
swga-0.4.0.data/data/bin/set_finder
swga-0.4.0.dist-info/DESCRIPTION.rst
swga-0.4.0.dist-info/METADATA
swga-0.4.0.dist-info/RECORD
swga-0.4.0.dist-info/WHEEL
swga-0.4.0.dist-info/eager_resources.txt
swga-0.4.0.dist-info/entry_points.txt
swga-0.4.0.dist-info/metadata.json
swga-0.4.0.dist-info/top_level.txt
