Metadata-Version: 2.0
Name: swga
Version: 0.4.0
Summary: Pipeline to select compatible primer sets for selective whole-genome amplification.
Home-page: https://github.com/eclarke/swga
Author: Erik Clarke
Author-email: ecl@mail.med.upenn.edu
License: LICENSE.txt
Platform: UNKNOWN
Classifier: Programming Language :: Python
Classifier: Development Status :: 4 - Beta
Classifier: Environment :: Console
Classifier: Intended Audience :: Science/Research
Classifier: License :: OSI Approved :: GNU General Public License (GPL)
Requires-Dist: argutils
Requires-Dist: click
Requires-Dist: melt
Requires-Dist: peewee
Requires-Dist: pyfaidx
Requires-Dist: pytest
Requires-Dist: pyyaml
Requires-Dist: semantic-version
